{
	"info": {
		"_postman_id": "685c31e1-5651-41cc-a6a0-4797be97a7fc",
		"name": "Test-Onfly",
		"schema": "https://schema.getpostman.com/json/collection/v2.1.0/collection.json",
		"_exporter_id": "17430979"
	},
	"item": [
		{
			"name": "Despesas",
			"item": [
				{
					"name": "Buscar todas as despesas",
					"event": [
						{
							"listen": "test",
							"script": {
								"exec": [
									"pm.test(\"Status code is 200\", function () {",
									"    pm.response.to.have.status(200);",
									"});"
								],
								"type": "text/javascript"
							}
						}
					],
					"request": {
						"auth": {
							"type": "bearer",
							"bearer": [
								{
									"key": "token",
									"value": "{{bearerToken}}",
									"type": "string"
								}
							]
						},
						"method": "GET",
						"header": [],
						"url": {
							"raw": "{{base_url}}/api/expenses",
							"host": [
								"{{base_url}}"
							],
							"path": [
								"api",
								"expenses"
							]
						},
						"description": "This is a GET request and it is used to \"get\" data from an endpoint. There is no request body for a GET request, but you can use query parameters to help specify the resource you want data on (e.g., in this request, we have `id=1`).\n\nA successful GET response will have a `200 OK` status, and should include some kind of response body - for example, HTML web content or JSON data."
					},
					"response": []
				},
				{
					"name": "Buscar despesa específica",
					"event": [
						{
							"listen": "test",
							"script": {
								"exec": [
									"pm.test(\"Status code is 200\", function () {",
									"    pm.response.to.have.status(200);",
									"});"
								],
								"type": "text/javascript"
							}
						}
					],
					"request": {
						"auth": {
							"type": "bearer",
							"bearer": [
								{
									"key": "token",
									"value": "{{bearerToken}}",
									"type": "string"
								}
							]
						},
						"method": "GET",
						"header": [],
						"url": {
							"raw": "{{base_url}}/api/expenses/{{expense_id}}",
							"host": [
								"{{base_url}}"
							],
							"path": [
								"api",
								"expenses",
								"{{expense_id}}"
							]
						},
						"description": "This is a GET request and it is used to \"get\" data from an endpoint. There is no request body for a GET request, but you can use query parameters to help specify the resource you want data on (e.g., in this request, we have `id=1`).\n\nA successful GET response will have a `200 OK` status, and should include some kind of response body - for example, HTML web content or JSON data."
					},
					"response": []
				},
				{
					"name": "Salvar despesa",
					"event": [
						{
							"listen": "test",
							"script": {
								"exec": [
									"pm.test(\"Successful POST request\", function () {",
									"    pm.expect(pm.response.code).to.be.oneOf([200, 201]);",
									"});",
									""
								],
								"type": "text/javascript"
							}
						}
					],
					"request": {
						"auth": {
							"type": "bearer",
							"bearer": [
								{
									"key": "token",
									"value": "{{bearerToken}}",
									"type": "string"
								}
							]
						},
						"method": "POST",
						"header": [],
						"body": {
							"mode": "raw",
							"raw": "{\n    \"description\":\"Descrição da despesa\",\n    \"user_id\": 1,\n    \"date\": \"24/01/2024\",\n    \"value\": \"250,33\"\n}",
							"options": {
								"raw": {
									"language": "json"
								}
							}
						},
						"url": {
							"raw": "{{base_url}}/api/expenses/",
							"host": [
								"{{base_url}}"
							],
							"path": [
								"api",
								"expenses",
								""
							]
						},
						"description": "This is a POST request, submitting data to an API via the request body. This request submits JSON data, and the data is reflected in the response.\n\nA successful POST request typically returns a `200 OK` or `201 Created` response code."
					},
					"response": []
				},
				{
					"name": "Editar despesa",
					"event": [
						{
							"listen": "test",
							"script": {
								"exec": [
									"pm.test(\"Successful POST request\", function () {",
									"    pm.expect(pm.response.code).to.be.oneOf([200, 201]);",
									"});",
									""
								],
								"type": "text/javascript"
							}
						}
					],
					"request": {
						"auth": {
							"type": "bearer",
							"bearer": [
								{
									"key": "token",
									"value": "{{bearerToken}}",
									"type": "string"
								}
							]
						},
						"method": "PUT",
						"header": [],
						"body": {
							"mode": "raw",
							"raw": "{\n    \"description\":\"Editando a despesa\",\n    \"user_id\": 1,\n    \"date\": \"24/01/2024\",\n    \"value\": \"250,33\"\n}",
							"options": {
								"raw": {
									"language": "json"
								}
							}
						},
						"url": {
							"raw": "{{base_url}}/api/expenses/{{expense_id}}",
							"host": [
								"{{base_url}}"
							],
							"path": [
								"api",
								"expenses",
								"{{expense_id}}"
							]
						},
						"description": "This is a POST request, submitting data to an API via the request body. This request submits JSON data, and the data is reflected in the response.\n\nA successful POST request typically returns a `200 OK` or `201 Created` response code."
					},
					"response": []
				},
				{
					"name": "Excluir despesa",
					"event": [
						{
							"listen": "test",
							"script": {
								"exec": [
									"pm.test(\"Successful DELETE request\", function () {",
									"    pm.expect(pm.response.code).to.be.oneOf([200, 202, 204]);",
									"});",
									""
								],
								"type": "text/javascript"
							}
						}
					],
					"request": {
						"auth": {
							"type": "bearer",
							"bearer": [
								{
									"key": "token",
									"value": "{{bearerToken}}",
									"type": "string"
								}
							]
						},
						"method": "DELETE",
						"header": [],
						"body": {
							"mode": "raw",
							"raw": "",
							"options": {
								"raw": {
									"language": "json"
								}
							}
						},
						"url": {
							"raw": "{{base_url}}/api/expenses/{{expense_id}}",
							"host": [
								"{{base_url}}"
							],
							"path": [
								"api",
								"expenses",
								"{{expense_id}}"
							]
						},
						"description": "This is a DELETE request, and it is used to delete data that was previously created via a POST request. You typically identify the entity being updated by including an identifier in the URL (eg. `id=1`).\n\nA successful DELETE request typically returns a `200 OK`, `202 Accepted`, or `204 No Content` response code."
					},
					"response": []
				}
			]
		},
		{
			"name": "Usuário",
			"item": [
				{
					"name": "Criar Usuário",
					"request": {
						"method": "POST",
						"header": [],
						"body": {
							"mode": "raw",
							"raw": "{\n    \"name\":\"Nome usuário\",\n    \"email\": \"email@valido.com\",\n    \"password\": \"min6caracteres\"\n}",
							"options": {
								"raw": {
									"language": "json"
								}
							}
						},
						"url": {
							"raw": "{{base_url}}/api/register",
							"host": [
								"{{base_url}}"
							],
							"path": [
								"api",
								"register"
							]
						}
					},
					"response": []
				},
				{
					"name": "Login",
					"request": {
						"method": "POST",
						"header": [],
						"body": {
							"mode": "raw",
							"raw": "{\n    \"email\": \"email@valido.com\",\n    \"password\": \"password\"\n}",
							"options": {
								"raw": {
									"language": "json"
								}
							}
						},
						"url": {
							"raw": "{{base_url}}/api/login",
							"host": [
								"{{base_url}}"
							],
							"path": [
								"api",
								"login"
							]
						}
					},
					"response": []
				},
				{
					"name": "Logout",
					"request": {
						"auth": {
							"type": "bearer",
							"bearer": [
								{
									"key": "token",
									"value": "{{bearerToken}}",
									"type": "string"
								}
							]
						},
						"method": "POST",
						"header": [],
						"body": {
							"mode": "formdata",
							"formdata": []
						},
						"url": {
							"raw": "{{base_url}}/api/logout",
							"host": [
								"{{base_url}}"
							],
							"path": [
								"api",
								"logout"
							]
						}
					},
					"response": []
				}
			]
		}
	],
	"event": [
		{
			"listen": "prerequest",
			"script": {
				"type": "text/javascript",
				"exec": [
					""
				]
			}
		},
		{
			"listen": "test",
			"script": {
				"type": "text/javascript",
				"exec": [
					""
				]
			}
		}
	],
	"variable": [
		{
			"key": "id",
			"value": "1"
		},
		{
			"key": "base_url",
			"value": "https://postman-rest-api-learner.glitch.me/"
		}
	]
}